universal_mcp_firecrawl/README.md
universal_mcp_firecrawl/__init__.py
universal_mcp_firecrawl/app.py
universal_mcp_firecrawl/server.py
universal_mcp_firecrawl-0.1.7.dist-info/METADATA
universal_mcp_firecrawl-0.1.7.dist-info/WHEEL
universal_mcp_firecrawl-0.1.7.dist-info/entry_points.txt
universal_mcp_firecrawl-0.1.7.dist-info/licenses/LICENSE
universal_mcp_firecrawl-0.1.7.dist-info/RECORD
